[
    {
        "host": "msfwifi.3g.qq.com",
        "port": 8080
    },
    {
        "host": "123.151.54.38",
        "port": 80
    },
    {
        "host": "183.47.98.90",
        "port": 8080
    },
    {
        "host": "183.47.98.25",
        "port": 443
    },
    {
        "host": "180.102.191.164",
        "port": 80
    },
    {
        "host": "42.81.184.206",
        "port": 8080
    },
    {
        "host": "42.81.179.212",
        "port": 80
    },
    {
        "host": "183.47.98.11",
        "port": 443
    },
    {
        "host": "114.222.112.90",
        "port": 14000
    }
]